<?xml version="1.0" encoding="UTF-8"?>
<objects serializationModel="Studio.01.10.00">
    <object class="EncodingSetting" id="{d695f616-96b4-4880-b456-a5827d21d2f9}">
        <property name="encodingFormat">
            <value>3</value>
        </property>
        <property name="quality">
            <value>37</value>
        </property>
        <relationship name="platform">
            <destination>{20d9fc6b-3e58-4f41-a41f-91b608405c81}</destination>
        </relationship>
        <relationship name="encodable">
            <destination>{9602ba53-d280-4bbb-ad2a-e02acb641e2d}</destination>
        </relationship>
    </object>
</objects>
